strawman/__init__.py
strawman/dummy_pandas.py
strawman/py.typed
strawman/utils.py
strawman-0.1.3.dist-info/LICENSE
strawman-0.1.3.dist-info/WHEEL
strawman-0.1.3.dist-info/METADATA
strawman-0.1.3.dist-info/RECORD
