Metadata-Version: 2.1
Name: strawman
Version: 0.1.3
Summary: Library for simple dummy objects
Home-page: https://github.com/dobraczka/strawman
License: MIT
Keywords: prototyping
Author: Daniel Obraczka
Author-email: obraczka@informatik.uni-leipzig.de
Requires-Python: >=3.8,<4.0
Classifier: Development Status :: 4 - Beta
Classifier: License :: OSI Approved :: MIT License
Classifier: Programming Language :: Python
Classifier: Programming Language :: Python :: 3
Classifier: Programming Language :: Python :: 3.8
Classifier: Programming Language :: Python :: 3.9
Classifier: Programming Language :: Python :: 3.10
Classifier: Programming Language :: Python :: 3.11
Classifier: Programming Language :: Python :: 3 :: Only
Classifier: Programming Language :: Python :: 3.10
Classifier: Programming Language :: Python :: 3.8
Classifier: Programming Language :: Python :: 3.9
Classifier: Topic :: Scientific/Engineering
Classifier: Topic :: Utilities
Provides-Extra: docs
Requires-Dist: mkdocs (>=1.4.2,<2.0.0) ; extra == "docs"
Requires-Dist: mkdocs-gen-files (>=0.4.0,<0.5.0) ; extra == "docs"
Requires-Dist: mkdocs-literate-nav (>=0.6.0,<0.7.0) ; extra == "docs"
Requires-Dist: mkdocs-material (>=9.0.9,<10.0.0) ; extra == "docs"
Requires-Dist: mkdocs-section-index (>=0.3.5,<0.4.0) ; extra == "docs"
Requires-Dist: mkdocstrings[python] (>=0.20.0,<0.21.0) ; extra == "docs"
Requires-Dist: numpy
Requires-Dist: pandas (>=1.0)
Project-URL: Bug Tracker, https://github.com/dobraczka/strawman/issues
Project-URL: Documentation, https://strawman.readthedocs.io
Project-URL: Repository, https://github.com/dobraczka/strawman
Project-URL: Source, https://github.com/dobraczka/strawman
